<?xml version="1.0" encoding="ISO-8859-1"?>
<!DOCTYPE hibernate-mapping
  PUBLIC "-//Hibernate/Hibernate Mapping DTD 3.0//EN" "http://hibernate.sourceforge.net/hibernate-mapping-3.0.dtd">
<hibernate-mapping package="de.ingrid.mdek.services.persistence.db.model">
   <class name="T011ObjServVersion" table="t011_obj_serv_version">
      <id name="id" type="long" column="id">
         <generator class="hilo"/>
      </id>
      <version name="version" type="integer" column="version"/>
      <property name="objServId" type="long" column="obj_serv_id"/>
      <property name="line" type="integer" column="line"/>
      <property name="servVersion" type="string" column="serv_version"/>

   </class>

</hibernate-mapping>